dnmf/DNMF.py
dnmf/__init__.py
dnmf_python-0.0.3.dist-info/LICENSE
dnmf_python-0.0.3.dist-info/METADATA
dnmf_python-0.0.3.dist-info/WHEEL
dnmf_python-0.0.3.dist-info/top_level.txt
dnmf_python-0.0.3.dist-info/RECORD
