Metadata-Version: 2.1
Name: dnmf-python
Version: 0.0.3
Summary: Unofficial Python implementation of the DNMF overlapping community detection algorithm
Home-page: https://github.com/Bani57/dnmf-python
Author: Andrej Janchevski
Author-email: andrej.janchevski@epfl.ch
License: UNKNOWN
Project-URL: Bug Tracker, https://github.com/Bani57/dnmf-python/issues
Platform: UNKNOWN
Classifier: Programming Language :: Python :: 3
Classifier: License :: OSI Approved :: MIT License
Classifier: Operating System :: OS Independent
Requires-Python: >=3.7
License-File: LICENSE
Requires-Dist: torch (>=1.9.1)
